<?xml version="1.0" encoding="UTF-8"?>
<!DOCTYPE xdrs-output SYSTEM "src/dtd/xdrs.dtd">
<xdrs-output version="'boxer v1.00 (unix build on 21 May 2021, 16:29:40)'">
<!-- ø Mr Jenninger will take the witness~stand on ø 13 May . --> 

<xdrs xml:id="xdrs1">
 <taggedtokens>
  <tagtoken xml:id="i1001">
   <tags>
     <tag type="verbnet" n="0">[]</tag>
     <tag type="tok">ø</tag>
     <tag type="cat">np/n</tag>
     <tag type="wordnet">O</tag>
     <tag type="sense">0</tag>
     <tag type="sym">ø</tag>
     <tag type="lemma">ø</tag>
     <tag type="sem">DEF</tag>
     <tag type="from">0</tag>
     <tag type="to">-1</tag>
   </tags>
  </tagtoken>
  <tagtoken xml:id="i1002">
   <tags>
     <tag type="tok">Mr</tag>
     <tag type="cat">n/n</tag>
     <tag type="sym">mr</tag>
     <tag type="lemma">mr</tag>
     <tag type="from">0</tag>
     <tag type="to">2</tag>
     <tag type="pos">NNP</tag>
     <tag type="sem">ROL</tag>
     <tag type="wordnet">mr.n.01</tag>
     <tag type="verbnet" n="1">[Title]</tag>
   </tags>
  </tagtoken>
  <tagtoken xml:id="i1003">
   <tags>
     <tag type="verbnet" n="0">[]</tag>
     <tag type="tok">Jenninger</tag>
     <tag type="cat">n</tag>
     <tag type="sym">jenninger</tag>
     <tag type="lemma">jenninger</tag>
     <tag type="from">3</tag>
     <tag type="to">12</tag>
     <tag type="pos">NNP</tag>
     <tag type="sem">PER</tag>
     <tag type="wordnet">male.n.02</tag>
   </tags>
  </tagtoken>
  <tagtoken xml:id="i1004">
   <tags>
     <tag type="verbnet" n="0">[]</tag>
     <tag type="tok">will</tag>
     <tag type="cat">(s:dcl\np)/(s:b\np)</tag>
     <tag type="sym">will</tag>
     <tag type="lemma">will</tag>
     <tag type="from">13</tag>
     <tag type="to">17</tag>
     <tag type="pos">MD</tag>
     <tag type="sem">FUT</tag>
     <tag type="wordnet">O</tag>
   </tags>
  </tagtoken>
  <tagtoken xml:id="i1005">
   <tags>
     <tag type="tok">take</tag>
     <tag type="cat">(s:b\np)/np</tag>
     <tag type="sym">take</tag>
     <tag type="lemma">take</tag>
     <tag type="from">18</tag>
     <tag type="to">22</tag>
     <tag type="pos">VB</tag>
     <tag type="sem">EXS</tag>
     <tag type="wordnet">take.v.22</tag>
     <tag type="verbnet" n="2">[Location,Theme]</tag>
   </tags>
  </tagtoken>
  <tagtoken xml:id="i1006">
   <tags>
     <tag type="verbnet" n="0">[]</tag>
     <tag type="tok">the</tag>
     <tag type="cat">np/n</tag>
     <tag type="sym">the</tag>
     <tag type="lemma">the</tag>
     <tag type="from">23</tag>
     <tag type="to">26</tag>
     <tag type="pos">DT</tag>
     <tag type="sem">DEF</tag>
     <tag type="wordnet">O</tag>
   </tags>
  </tagtoken>
  <tagtoken xml:id="i1007">
   <tags>
     <tag type="verbnet" n="0">[]</tag>
     <tag type="tok">witness~stand</tag>
     <tag type="cat">n</tag>
     <tag type="sym">witness~stand</tag>
     <tag type="lemma">witness~stand</tag>
     <tag type="from">27</tag>
     <tag type="to">40</tag>
     <tag type="pos">NN</tag>
     <tag type="sem">CON</tag>
     <tag type="wordnet">witness_stand.n.01</tag>
   </tags>
  </tagtoken>
  <tagtoken xml:id="i1008">
   <tags>
     <tag type="tok">on</tag>
     <tag type="cat">((s:dcl\np)\(s:dcl\np))/np</tag>
     <tag type="sym">on</tag>
     <tag type="lemma">on</tag>
     <tag type="from">41</tag>
     <tag type="to">43</tag>
     <tag type="pos">IN</tag>
     <tag type="sem">REL</tag>
     <tag type="wordnet">O</tag>
     <tag type="verbnet" n="1">[Time]</tag>
   </tags>
  </tagtoken>
  <tagtoken xml:id="i1009">
   <tags>
     <tag type="verbnet" n="0">[]</tag>
     <tag type="tok">ø</tag>
     <tag type="cat">np/n</tag>
     <tag type="wordnet">O</tag>
     <tag type="sense">0</tag>
     <tag type="sym">ø</tag>
     <tag type="lemma">ø</tag>
     <tag type="sem">DEF</tag>
     <tag type="from">44</tag>
     <tag type="to">-1</tag>
   </tags>
  </tagtoken>
  <tagtoken xml:id="i1010">
   <tags>
     <tag type="tok">13</tag>
     <tag type="cat">n/n</tag>
     <tag type="sym">13</tag>
     <tag type="lemma">13</tag>
     <tag type="from">44</tag>
     <tag type="to">46</tag>
     <tag type="pos">CD</tag>
     <tag type="sem">DOM</tag>
     <tag type="wordnet">O</tag>
     <tag type="verbnet" n="1">[Equal]</tag>
   </tags>
  </tagtoken>
  <tagtoken xml:id="i1011">
   <tags>
     <tag type="verbnet" n="0">[]</tag>
     <tag type="tok">May</tag>
     <tag type="cat">n</tag>
     <tag type="sym">may</tag>
     <tag type="lemma">may</tag>
     <tag type="from">47</tag>
     <tag type="to">50</tag>
     <tag type="pos">NNP</tag>
     <tag type="sem">MOY</tag>
     <tag type="wordnet">O</tag>
   </tags>
  </tagtoken>
  <tagtoken xml:id="i1012">
   <tags>
     <tag type="verbnet" n="0">[]</tag>
     <tag type="tok">.</tag>
     <tag type="cat">s:dcl\s:dcl</tag>
     <tag type="sym">.</tag>
     <tag type="lemma">.</tag>
     <tag type="from">50</tag>
     <tag type="to">51</tag>
     <tag type="pos">.</tag>
     <tag type="sem">NIL</tag>
     <tag type="wordnet">O</tag>
   </tags>
  </tagtoken>
 </taggedtokens>
 <drs label="b1">
  <domain>
   <dr label="b1" name="t1" from="0" to="0"></dr>
   <dr label="b2" name="x1" from="0" to="-1"></dr>
   <dr label="b2" name="x2" from="0" to="2"></dr>
   <dr label="b3" name="x3" from="23" to="26"></dr>
   <dr label="b1" name="e1" from="18" to="22"></dr>
  </domain>
  <conds>
   <cond label="b2">
    <pred arg="x2" symbol="mr" synset="mr.n.01" from="0" to="2"></pred>
   </cond>
   <cond label="b2">
    <pred arg="x1" symbol="male" synset="male.n.02" from="3" to="12"></pred>
   </cond>
   <cond label="b2">
    <named arg="x1" symbol="jenninger" from="3" to="12"></named>
   </cond>
   <cond label="b2">
    <rel arg1="x1" arg2="x2" symbol="Title" framenet="Title" from="0" to="2"></rel>
   </cond>
   <cond label="b1">
    <pred arg="t1" symbol="time" synset="time.n.08" from="0" to="0"></pred>
   </cond>
   <cond label="b1">
    <rel arg1="t1" arg2="05" symbol="MonthOfYear" framenet="MonthOfYear" from="47" to="50"></rel>
   </cond>
   <cond label="b1">
    <rel arg1="t1" arg2="13" symbol="DayOfMonth" framenet="DayOfMonth" from="44" to="46"></rel>
   </cond>
   <cond label="b1">
    <comp symbol="TSU" arg1="t1" arg2="now" from="13" to="17"></comp>
   </cond>
   <cond label="b1">
    <pred arg="e1" symbol="take" synset="take.v.22" from="18" to="22"></pred>
   </cond>
   <cond label="b1">
    <rel arg1="e1" arg2="t1" symbol="Time" framenet="Time" from="0" to="0"></rel>
   </cond>
   <cond label="b1">
    <rel arg1="e1" arg2="x3" symbol="Location" framenet="Containing@Container" from="18" to="22"></rel>
   </cond>
   <cond label="b1">
    <rel arg1="e1" arg2="x1" symbol="Theme" framenet="Carry_goods@Goods" from="18" to="22"></rel>
   </cond>
   <cond label="b3">
    <pred arg="x3" symbol="witness_stand" synset="witness_stand.n.01" from="27" to="40"></pred>
   </cond>
  </conds>
 </drs>
</xdrs>
</xdrs-output>
