<?xml version="1.0" encoding="UTF-8"?>
<!DOCTYPE xdrs-output SYSTEM "src/dtd/xdrs.dtd">
<xdrs-output version="'boxer v1.00 (unix build on 21 May 2021, 16:29:40)'">
<!-- I was crying . --> 

<xdrs xml:id="xdrs1">
 <taggedtokens>
  <tagtoken xml:id="i1001">
   <tags>
     <tag type="verbnet" n="0">[]</tag>
     <tag type="tok">I</tag>
     <tag type="cat">np</tag>
     <tag type="sym">speaker</tag>
     <tag type="lemma">speaker</tag>
     <tag type="from">0</tag>
     <tag type="to">1</tag>
     <tag type="pos">PRP</tag>
     <tag type="sem">PRO</tag>
     <tag type="wordnet">O</tag>
   </tags>
  </tagtoken>
  <tagtoken xml:id="i1002">
   <tags>
     <tag type="verbnet" n="0">[]</tag>
     <tag type="tok">was</tag>
     <tag type="cat">(s:dcl\np)/(s:ng\np)</tag>
     <tag type="sym">be</tag>
     <tag type="lemma">be</tag>
     <tag type="from">2</tag>
     <tag type="to">5</tag>
     <tag type="pos">VBD</tag>
     <tag type="sem">PST</tag>
     <tag type="wordnet">O</tag>
   </tags>
  </tagtoken>
  <tagtoken xml:id="i1003">
   <tags>
     <tag type="tok">crying</tag>
     <tag type="cat">s:ng\np</tag>
     <tag type="sym">cry</tag>
     <tag type="lemma">cry</tag>
     <tag type="from">6</tag>
     <tag type="to">12</tag>
     <tag type="pos">VBG</tag>
     <tag type="sem">EXG</tag>
     <tag type="wordnet">cry.v.02</tag>
     <tag type="verbnet" n="1">[Agent]</tag>
   </tags>
  </tagtoken>
  <tagtoken xml:id="i1004">
   <tags>
     <tag type="verbnet" n="0">[]</tag>
     <tag type="tok">.</tag>
     <tag type="cat">s:dcl\s:dcl</tag>
     <tag type="sym">.</tag>
     <tag type="lemma">.</tag>
     <tag type="from">12</tag>
     <tag type="to">13</tag>
     <tag type="pos">.</tag>
     <tag type="sem">NIL</tag>
     <tag type="wordnet">O</tag>
   </tags>
  </tagtoken>
 </taggedtokens>
 <drs label="b1">
  <domain>
   <dr label="b1" name="x1" from="0" to="1"></dr>
   <dr label="b1" name="e1" from="6" to="12"></dr>
   <dr label="b1" name="t1" from="2" to="5"></dr>
  </domain>
  <conds>
   <cond label="b1">
    <pred arg="x1" symbol="person" synset="person.n.01" from="0" to="1"></pred>
   </cond>
   <cond label="b1">
    <comp symbol="EQU" arg1="x1" arg2="speaker" from="0" to="1"></comp>
   </cond>
   <cond label="b1">
    <pred arg="t1" symbol="time" synset="time.n.08" from="2" to="5"></pred>
   </cond>
   <cond label="b1">
    <comp symbol="TPR" arg1="t1" arg2="now" from="2" to="5"></comp>
   </cond>
   <cond label="b1">
    <pred arg="e1" symbol="cry" synset="cry.v.02" from="6" to="12"></pred>
   </cond>
   <cond label="b1">
    <rel arg1="e1" arg2="t1" symbol="Time" framenet="Time" from="2" to="5"></rel>
   </cond>
   <cond label="b1">
    <rel arg1="e1" arg2="x1" symbol="Agent" framenet="Excreting@Excreter" from="6" to="12"></rel>
   </cond>
  </conds>
 </drs>
</xdrs>
</xdrs-output>
